LICENSE
README.md
setup.py
adam_sdk/AdamManager.py
adam_sdk/JsonParser.py
adam_sdk/ServoConnection.py
adam_sdk/__init__.py
adam_sdk.egg-info/PKG-INFO
adam_sdk.egg-info/SOURCES.txt
adam_sdk.egg-info/dependency_links.txt
adam_sdk.egg-info/requires.txt
adam_sdk.egg-info/top_level.txt
adam_sdk/Controllers/JointController.py
adam_sdk/Controllers/MecanumMoveController.py
adam_sdk/Controllers/MotorController.py
adam_sdk/Models/IMoveController.py
adam_sdk/Models/Joint.py
adam_sdk/Models/Motor.py
adam_sdk/Models/MotorCommand.py
adam_sdk/Models/MotorEnum.py
adam_sdk/Models/SerializableCommands.py